mrio_common_metadata/__init__.py
mrio_common_metadata/utils.py
mrio_common_metadata/version.py
mrio_common_metadata/conversion/__init__.py
mrio_common_metadata/conversion/exiobase_3_hybrid_io/__init__.py
mrio_common_metadata/conversion/exiobase_3_hybrid_io/datapackage.py
mrio_common_metadata/conversion/exiobase_3_hybrid_io/utils.py
mrio_common_metadata/conversion/exiobase_3_hybrid_io/version_config.py
mrio_common_metadata/conversion/exiobase_3_hybrid_su/__init__.py
mrio_common_metadata/conversion/exiobase_3_hybrid_su/datapackage.py
mrio_common_metadata/conversion/exiobase_3_hybrid_su/utils.py
mrio_common_metadata/conversion/exiobase_3_hybrid_su/version_config.py
mrio_common_metadata-0.2.1.dist-info/LICENSE
mrio_common_metadata-0.2.1.dist-info/METADATA
mrio_common_metadata-0.2.1.dist-info/WHEEL
mrio_common_metadata-0.2.1.dist-info/top_level.txt
mrio_common_metadata-0.2.1.dist-info/RECORD
